CHANGELOG.txt
LICENCE.txt
MANIFEST.in
README.txt
setup.py
example/read.py
example/send.py
example/send_and_Read.py
iotellme/__init__.py
iotellme.egg-info/PKG-INFO
iotellme.egg-info/SOURCES.txt
iotellme.egg-info/dependency_links.txt
iotellme.egg-info/requires.txt
iotellme.egg-info/top_level.txt