Metadata-Version: 2.1
Name: iotellme
Version: 1.7.0
Summary: Helping developers easily build, test, manage, and scale applications internet of things faster than ever before.
Home-page: https://iotellme.io/
Author: iotellme LLC
Author-email: abdulmalektaleb2022@gmail.com
License: MIT
Keywords: iotellme,Token,Send,Read,Write1
Platform: UNKNOWN
Classifier: Development Status :: 5 - Production/Stable
Classifier: Intended Audience :: Developers
Classifier: License :: OSI Approved :: MIT License
Classifier: Programming Language :: Python :: 3
Classifier: Operating System :: Unix
Classifier: Operating System :: MacOS :: MacOS X
Classifier: Operating System :: Microsoft :: Windows :: Windows 10
License-File: LICENCE.txt
